couchpotato/__init__.py
couchpotato/decorator.py
couchpotato/very/__init__.py
couchpotato/very/lazy.py
couchpotato-0.1.0.dist-info/WHEEL
couchpotato-0.1.0.dist-info/METADATA
couchpotato-0.1.0.dist-info/RECORD
