Metadata-Version: 1.2
Name: couchpotato
Version: 0.1.0
Summary: The couchpotato module is used to lazily evaluate functions.
Home-page: https://github.com/buckbaskin/couchpotato
License: UNKNOWN
Author: William Baskin
Author-email: mobile.wbaskin@gmail.com
